latex_generators/__init__.py
latex_generators/latex_generator.py
latex_generator_hse_spb_youka-0.1.1.dist-info/METADATA
latex_generator_hse_spb_youka-0.1.1.dist-info/WHEEL
latex_generator_hse_spb_youka-0.1.1.dist-info/top_level.txt
latex_generator_hse_spb_youka-0.1.1.dist-info/RECORD
