Metadata-Version: 2.2
Name: latex_generator_hse_spb_youka
Version: 0.1.1
Summary: Библиотека для генерации LaTeX-кода таблиц и изображений
Home-page: https://github.com/Youka4/latex_gen
Author: Dmitriy Yukachev
Author-email: dim.youka4@gmail.com
Classifier: Programming Language :: Python :: 3
Classifier: License :: OSI Approved :: MIT License
Classifier: Operating System :: OS Independent
Requires-Python: >=3.8
Dynamic: author
Dynamic: author-email
Dynamic: classifier
Dynamic: description
Dynamic: description-content-type
Dynamic: home-page
Dynamic: requires-python
Dynamic: summary
